<Alloy>
	<Window class="container">
		<View id="topMenu">
			<View class="topButton"  onClick="infoPage">
				<ImageView class="topImage" image="info.jpg"></ImageView>
			</View>
			<View class="topButtonActive" onClick="videoPage">
				<ImageView class="topImage" image="video.png"></ImageView>
			</View>
			<View class="topButton" onClick="exercisePage">
				<ImageView class="topImage" image="exercise.png"></ImageView>
			</View>
			<View class="topButton" onClick="statisticsPage">
				<ImageView class="topImage" image="graph.png"></ImageView>
			</View>
		</View>
	</Window>
</Alloy>